fairness_ranking/__init__.py
fairness_ranking/ranking.py
fairness_ranking-0.1.1.dist-info/METADATA
fairness_ranking-0.1.1.dist-info/WHEEL
fairness_ranking-0.1.1.dist-info/top_level.txt
fairness_ranking-0.1.1.dist-info/RECORD
