Metadata-Version: 2.2
Name: fairness_ranking
Version: 0.1.1
Summary: A package for generating synthetic data, reranking students, and calculating fairness metrics.
Author: Mallak Alkhathlan
Author-email: malkhathlan@wpi.edu
Classifier: Programming Language :: Python :: 3
Classifier: License :: OSI Approved :: MIT License
Classifier: Operating System :: OS Independent
Requires-Python: >=3.6
Requires-Dist: pandas
Requires-Dist: numpy
Requires-Dist: scikit-learn
Dynamic: author
Dynamic: author-email
Dynamic: classifier
Dynamic: description
Dynamic: description-content-type
Dynamic: requires-dist
Dynamic: requires-python
Dynamic: summary
